repex.py
repex-1.2.2.dist-info/DESCRIPTION.rst
repex-1.2.2.dist-info/LICENSE.txt
repex-1.2.2.dist-info/METADATA
repex-1.2.2.dist-info/RECORD
repex-1.2.2.dist-info/WHEEL
repex-1.2.2.dist-info/entry_points.txt
repex-1.2.2.dist-info/metadata.json
repex-1.2.2.dist-info/top_level.txt
