Metadata-Version: 2.0
Name: repex
Version: 1.2.2
Summary: sed on steroids
Home-page: https://github.com/cloudify-cosmo/repex
Author: Gigaspaces
Author-email: cosmo-admin@gigaspaces.com
License: LICENSE
Platform: All
Classifier: Development Status :: 5 - Production/Stable
Classifier: Programming Language :: Python
Classifier: Programming Language :: Python :: 2.6
Classifier: Programming Language :: Python :: 2.7
Classifier: Programming Language :: Python :: 3
Classifier: Programming Language :: Python :: 3.3
Classifier: Programming Language :: Python :: 3.4
Classifier: Programming Language :: Python :: 3.5
Classifier: Programming Language :: Python :: 3.6
Classifier: Natural Language :: English
Classifier: Environment :: Console
Classifier: Intended Audience :: Developers
Classifier: Intended Audience :: Information Technology
Classifier: Intended Audience :: System Administrators
Classifier: License :: OSI Approved :: Apache Software License
Classifier: Operating System :: MacOS :: MacOS X
Classifier: Operating System :: POSIX :: Linux
Classifier: Operating System :: Microsoft
Classifier: Topic :: Software Development :: Libraries :: Python Modules
Requires-Dist: click (==6.7)
Requires-Dist: pyyaml (==3.12)
Requires-Dist: jsonschema (==2.5.1)
